{"format":1,"version":"4.4.1","settings":"3093a1f92208c10d26e4dac5d54b4f75","files":{"inaeternum_settings_py":{"hash":"6f8180613a840326cdae392f7478bfd6","index":{"nums":[1,18,0,0,0,0,0],"html_filename":"inaeternum_settings_py.html","relative_filename":"inaeternum\\settings.py"}},"manage_py":{"hash":"b18aa24d03c8ce3b8695abf0459cef83","index":{"nums":[1,13,0,6,0,0,0],"html_filename":"manage_py.html","relative_filename":"manage.py"}},"polls_admin_py":{"hash":"5d4792320c6b7c389624b57676451284","index":{"nums":[1,3,0,0,0,0,0],"html_filename":"polls_admin_py.html","relative_filename":"polls\\admin.py"}},"polls_apps_py":{"hash":"82507c900a501a01104dcfa61edb6e8c","index":{"nums":[1,3,0,0,0,0,0],"html_filename":"polls_apps_py.html","relative_filename":"polls\\apps.py"}},"polls_models_py":{"hash":"cf11261eb7ef674a738c33be94aee482","index":{"nums":[1,21,0,19,0,0,0],"html_filename":"polls_models_py.html","relative_filename":"polls\\models.py"}}}}